swarmauri_tokens_tlsboundjwt/TlsBoundJWTTokenService.py
swarmauri_tokens_tlsboundjwt/__init__.py
swarmauri_tokens_tlsboundjwt-0.2.0.dev4.dist-info/LICENSE
swarmauri_tokens_tlsboundjwt-0.2.0.dev4.dist-info/METADATA
swarmauri_tokens_tlsboundjwt-0.2.0.dev4.dist-info/WHEEL
swarmauri_tokens_tlsboundjwt-0.2.0.dev4.dist-info/entry_points.txt
swarmauri_tokens_tlsboundjwt-0.2.0.dev4.dist-info/RECORD
