Metadata-Version: 2.3
Name: swarmauri_tokens_tlsboundjwt
Version: 0.2.0.dev4
Summary: mTLS-bound JWT token service for Swarmauri
License: Apache-2.0
Author: Swarmauri
Author-email: opensource@swarmauri.com
Requires-Python: >=3.10,<3.13
Classifier: License :: OSI Approved :: Apache Software License
Classifier: Natural Language :: English
Classifier: Programming Language :: Python :: 3.10
Classifier: Programming Language :: Python :: 3.11
Classifier: Programming Language :: Python :: 3.12
Classifier: Programming Language :: Python :: 3.13
Classifier: Development Status :: 3 - Alpha
Classifier: Intended Audience :: Developers
Classifier: Topic :: Security :: Cryptography
Provides-Extra: cbor
Provides-Extra: xml
Requires-Dist: cbor2 ; extra == "cbor"
Requires-Dist: swarmauri_base
Requires-Dist: swarmauri_core
Requires-Dist: xmltodict ; extra == "xml"
